autoblockchainify/__init__.py
autoblockchainify/commit.py
autoblockchainify/config.py
autoblockchainify/daemon.py
autoblockchainify/deltat.py
autoblockchainify/mail.py
autoblockchainify/version.py
autoblockchainify-1.0.1.dist-info/LICENSE.md
autoblockchainify-1.0.1.dist-info/METADATA
autoblockchainify-1.0.1.dist-info/WHEEL
autoblockchainify-1.0.1.dist-info/entry_points.txt
autoblockchainify-1.0.1.dist-info/top_level.txt
autoblockchainify-1.0.1.dist-info/RECORD
