Metadata-Version: 2.1
Name: autoblockchainify
Version: 1.0.1
Summary: Turn a directory into a git-based Blockchain
Home-page: https://gitlab.com/zeitgitter/autoblockchainify
Author: Marcel Waldvogel
Author-email: marcel.waldvogel@trifence.ch
License: AGPLv3
Classifier: Development Status :: 4 - Beta
Classifier: Environment :: No Input/Output (Daemon)
Classifier: Intended Audience :: Information Technology
Classifier: Programming Language :: Python
Classifier: License :: OSI Approved :: GNU Affero General Public License v3
Classifier: Operating System :: OS Independent
Classifier: Natural Language :: English
Classifier: Topic :: Software Development :: Version Control :: Git
Classifier: Topic :: Security
Requires-Python: >=3.7
License-File: LICENSE.md
Requires-Dist: configargparse (~=1.2)
Requires-Dist: deltat (>=1.0.1)
Requires-Dist: git-timestamp (>=1.0.4)
Requires-Dist: pygit2
Requires-Dist: setuptools
Requires-Dist: signale-logging (>=0.5.3)
